petrosim/models/ecafc/driver.py
petrosim/models/ecafc/ecafc.py
petrosim/models/ecafc/equilibration.py
petrosim/models/ecafc/example.in
petrosim/models/ecafc/loader.py
petrosim/models/ecafc/test/test.in
petrosim/models/ecafc/test/test_ecafc.py
petrosim/models/ecafc/test/test_equilibration.py
petrosim/models/ecrafc/driver.py
petrosim/models/ecrafc/ecrafc.py
petrosim/models/ecrafc/equilibration.py
petrosim/models/ecrafc/loader.py
petrosim/results/plotter.py
petrosim/results/results.py
petrosim/utils/generate_example_input.py
petrosim-0.0.4.dist-info/LICENSE
petrosim-0.0.4.dist-info/METADATA
petrosim-0.0.4.dist-info/WHEEL
petrosim-0.0.4.dist-info/top_level.txt
petrosim-0.0.4.dist-info/RECORD
