Metadata-Version: 2.1
Name: petrosim
Version: 0.0.4
Summary: A collection of petrological simulation tools.
Author: Ryne C. Johnston
Author-email: johnston.ryne@gmail.com
License: MIT
Project-URL: Source, https://github.com/rynecjohnston/petrosim/
Project-URL: Tracker, https://github.com/rynecjohnston/petrosim/issues
Classifier: Programming Language :: Python :: 3
Classifier: License :: OSI Approved :: MIT License
Classifier: Operating System :: OS Independent
Requires-Python: >=3.8
License-File: LICENSE
Requires-Dist: setuptools (>=61.0)
Requires-Dist: ruamel.yaml (>=0.15)
Requires-Dist: voluptuous (>=0.13)
Requires-Dist: numpy (>=1.19)
Requires-Dist: matplotlib (>=3.6.2)
Requires-Dist: pytest (>=6.2)
